README.md
setup.cfg
setup.py
eksternlab/__init__.py
eksternlab/lane.py
eksternlab/splines.py
eksternlab/util.py
eksternlab.egg-info/PKG-INFO
eksternlab.egg-info/SOURCES.txt
eksternlab.egg-info/dependency_links.txt
eksternlab.egg-info/requires.txt
eksternlab.egg-info/top_level.txt
test/test_lane.py
test/test_splines.py