Metadata-Version: 1.1
Name: eksternlab
Version: 1.2
Summary: Useful scripts for NTNU lab for engineers
Home-page: https://github.com/davidkleiven/eksternlab
Author: David Kleiven
Author-email: david.kleiven@ntnu.no
License: UNKNOWN
Download-URL: https://github.com/davidkleiven/eksternlab/archive/v1.2.tar.gz
Platform: UNKNOWN
Classifier: Development Status :: 4 - Beta
Classifier: Programming Language :: Python :: 3
Classifier: Programming Language :: Python :: 3.4
Classifier: Programming Language :: Python :: 3.5
Classifier: Programming Language :: Python :: 3.6
Classifier: Programming Language :: Python :: 3.7
Classifier: Programming Language :: Python :: 2.7
